{
  "id": 4272771,
  "name": "Commonwealth vs. Joseph Limone",
  "name_abbreviation": "Commonwealth v. Limone",
  "decision_date": "2011-11-18",
  "docket_number": "",
  "first_page": "834",
  "last_page": "843",
  "citations": [
    {
      "type": "official",
      "cite": "460 Mass. 834"
    }
  ],
  "court": {
    "name_abbreviation": "Mass.",
    "id": 8825,
    "name": "Massachusetts Supreme Judicial Court"
  },
  "jurisdiction": {
    "id": 4,
    "name_long": "Massachusetts",
    "name": "Mass."
  },
  "cites_to": [
    {
      "cite": "423 Mass. 275",
      "category": "reporters:state",
      "reporter": "Mass.",
      "case_ids": [
        1028017
      ],
      "year": 1996,
      "pin_cites": [
        {
          "page": "281",
          "parenthetical": "relaxing requirements for citizen's arrest for felony, where \"citizen\" is police officer acting outside his jurisdiction"
        }
      ],
      "opinion_index": 0,
      "case_paths": [
        "/mass/423/0275-01"
      ]
    },
    {
      "cite": "419 Mass. 192",
      "category": "reporters:state",
      "reporter": "Mass.",
      "case_ids": [
        823669
      ],
      "year": 1994,
      "pin_cites": [
        {
          "page": "198-200"
        }
      ],
      "opinion_index": 0,
      "case_paths": [
        "/mass/419/0192-01"
      ]
    },
    {
      "cite": "166 Wis. 2d 243",
      "category": "reporters:state",
      "reporter": "Wis. 2d",
      "case_ids": [
        8666874
      ],
      "year": 1991,
      "pin_cites": [
        {
          "page": "246-249"
        }
      ],
      "opinion_index": 0,
      "case_paths": [
        "/wis-2d/166/0243-01"
      ]
    },
    {
      "cite": "205 W. Va. 72",
      "category": "reporters:state",
      "reporter": "W. Va.",
      "case_ids": [
        11644157
      ],
      "year": 1999,
      "pin_cites": [
        {
          "page": "80-83"
        }
      ],
      "opinion_index": 0,
      "case_paths": [
        "/w-va/205/0072-01"
      ]
    },
    {
      "cite": "288 Mass. 294",
      "category": "reporters:state",
      "reporter": "Mass.",
      "case_ids": [
        486588
      ],
      "weight": 2,
      "year": 1934,
      "pin_cites": [
        {
          "page": "297-299"
        }
      ],
      "opinion_index": 0,
      "case_paths": [
        "/mass/288/0294-01"
      ]
    },
    {
      "cite": "400 Mass. 369",
      "category": "reporters:state",
      "reporter": "Mass.",
      "case_ids": [
        880017
      ],
      "weight": 8,
      "year": 1987,
      "pin_cites": [
        {
          "parenthetical": "Tynes"
        },
        {
          "page": "372, 373-374"
        },
        {
          "page": "370"
        },
        {
          "page": "371"
        },
        {
          "page": "372-374"
        }
      ],
      "opinion_index": 0,
      "case_paths": [
        "/mass/400/0369-01"
      ]
    },
    {
      "cite": "73 Mass. App. Ct. 828",
      "category": "reporters:state",
      "reporter": "Mass. App. Ct.",
      "case_ids": [
        3830905
      ],
      "year": 2009,
      "pin_cites": [
        {
          "page": "831"
        }
      ],
      "opinion_index": 0,
      "case_paths": [
        "/mass-app-ct/73/0828-01"
      ]
    },
    {
      "cite": "392 U.S. 1",
      "category": "reporters:federal",
      "reporter": "U.S.",
      "case_ids": [
        6167798
      ],
      "year": 1968,
      "pin_cites": [
        {
          "page": "21"
        }
      ],
      "opinion_index": 0,
      "case_paths": [
        "/us/392/0001-01"
      ]
    },
    {
      "cite": "408 Mass. 136",
      "category": "reporters:state",
      "reporter": "Mass.",
      "case_ids": [
        3891639
      ],
      "weight": 2,
      "year": 1990,
      "pin_cites": [
        {
          "page": "141"
        }
      ],
      "opinion_index": 0,
      "case_paths": [
        "/mass/408/0136-01"
      ]
    },
    {
      "cite": "457 Mass. 107",
      "category": "reporters:state",
      "reporter": "Mass.",
      "case_ids": [
        4269196
      ],
      "weight": 4,
      "year": 2010,
      "pin_cites": [
        {
          "page": "111",
          "parenthetical": "chasing passenger of vehicle involved in police chase on foot and yelling \"Stop, police,\" did not communicate intent to arrest"
        },
        {
          "page": "110-111"
        },
        {
          "parenthetical": "\"an intent to stop for questioning is not identical to an intent to effectuate an arrest\""
        },
        {
          "page": "110-111"
        }
      ],
      "opinion_index": 0,
      "case_paths": [
        "/mass/457/0107-01"
      ]
    },
    {
      "cite": "433 Mass. 135",
      "category": "reporters:state",
      "reporter": "Mass.",
      "case_ids": [
        343569
      ],
      "year": 2001,
      "pin_cites": [
        {
          "page": "145"
        }
      ],
      "opinion_index": 0,
      "case_paths": [
        "/mass/433/0135-01"
      ]
    },
    {
      "cite": "459 Mass. 572",
      "category": "reporters:state",
      "reporter": "Mass.",
      "case_ids": [
        4270756
      ],
      "year": 2011,
      "pin_cites": [
        {
          "page": "580"
        }
      ],
      "opinion_index": 0,
      "case_paths": [
        "/mass/459/0572-01"
      ]
    },
    {
      "cite": "457 Mass. 152",
      "category": "reporters:state",
      "reporter": "Mass.",
      "case_ids": [
        4269259
      ],
      "year": 2010,
      "pin_cites": [
        {
          "page": "154-159",
          "parenthetical": "compliance with statute requiring police to allow arrested individual's telephone call depends on moment of arrest"
        }
      ],
      "opinion_index": 0,
      "case_paths": [
        "/mass/457/0152-01"
      ]
    },
    {
      "cite": "458 Mass. 684",
      "category": "reporters:state",
      "reporter": "Mass.",
      "case_ids": [
        4270579
      ],
      "year": 2011,
      "pin_cites": [
        {
          "page": "694-697",
          "parenthetical": "compliance with six-hour safe harbor for interrogating arrested individuals depends on moment of arrest"
        }
      ],
      "opinion_index": 0,
      "case_paths": [
        "/mass/458/0684-01"
      ]
    },
    {
      "cite": "430 Mass. 341",
      "category": "reporters:state",
      "reporter": "Mass.",
      "case_ids": [
        1157270
      ],
      "year": 1999,
      "opinion_index": 0,
      "case_paths": [
        "/mass/430/0341-01"
      ]
    },
    {
      "cite": "409 Mass. 284",
      "category": "reporters:state",
      "reporter": "Mass.",
      "case_ids": [
        3893220
      ],
      "year": 1991,
      "pin_cites": [
        {
          "page": "287"
        }
      ],
      "opinion_index": 0,
      "case_paths": [
        "/mass/409/0284-01"
      ]
    },
    {
      "cite": "456 Mass. 528",
      "category": "reporters:state",
      "reporter": "Mass.",
      "case_ids": [
        3668478
      ],
      "weight": 2,
      "year": 2010,
      "pin_cites": [
        {
          "page": "530-531"
        },
        {
          "page": "532"
        }
      ],
      "opinion_index": 0,
      "case_paths": [
        "/mass/456/0528-01"
      ]
    },
    {
      "cite": "435 Mass. 440",
      "category": "reporters:state",
      "reporter": "Mass.",
      "case_ids": [
        993858
      ],
      "year": 2001,
      "pin_cites": [
        {
          "page": "442-444"
        }
      ],
      "opinion_index": 0,
      "case_paths": [
        "/mass/435/0440-01"
      ]
    },
    {
      "cite": "398 Mass. 247",
      "category": "reporters:state",
      "reporter": "Mass.",
      "case_ids": [
        877683
      ],
      "weight": 6,
      "year": 1986,
      "pin_cites": [
        {
          "page": "249",
          "parenthetical": "Grise"
        },
        {
          "page": "250-251"
        },
        {
          "page": "250-251"
        }
      ],
      "opinion_index": 0,
      "case_paths": [
        "/mass/398/0247-01"
      ]
    },
    {
      "cite": "405 Mass. 646",
      "category": "reporters:state",
      "reporter": "Mass.",
      "case_ids": [
        3882665
      ],
      "year": 1989,
      "pin_cites": [
        {
          "page": "655"
        }
      ],
      "opinion_index": 0,
      "case_paths": [
        "/mass/405/0646-01"
      ]
    },
    {
      "cite": "393 Mass. 204",
      "category": "reporters:state",
      "reporter": "Mass.",
      "case_ids": [
        894372
      ],
      "year": 1984,
      "pin_cites": [
        {
          "page": "211-212"
        }
      ],
      "opinion_index": 0,
      "case_paths": [
        "/mass/393/0204-01"
      ]
    },
    {
      "cite": "371 U.S. 471",
      "category": "reporters:federal",
      "reporter": "U.S.",
      "case_ids": [
        450611
      ],
      "year": 1963,
      "pin_cites": [
        {
          "page": "488"
        }
      ],
      "opinion_index": 0,
      "case_paths": [
        "/us/371/0471-01"
      ]
    },
    {
      "cite": "460 Mass. 277",
      "category": "reporters:state",
      "reporter": "Mass.",
      "case_ids": [
        4272234
      ],
      "year": 2011,
      "pin_cites": [
        {
          "page": "279"
        }
      ],
      "opinion_index": 0,
      "case_paths": [
        "/mass/460/0277-01"
      ]
    },
    {
      "cite": "77 Mass. App. Ct. 903",
      "category": "reporters:state",
      "reporter": "Mass. App. Ct.",
      "case_ids": [
        3838495
      ],
      "weight": 4,
      "year": 2010,
      "pin_cites": [
        {
          "page": "905",
          "parenthetical": "Limone"
        },
        {
          "page": "904-905"
        },
        {
          "page": "905"
        }
      ],
      "opinion_index": 0,
      "case_paths": [
        "/mass-app-ct/77/0903-01"
      ]
    }
  ],
  "analysis": {
    "cardinality": 936,
    "char_count": 21982,
    "ocr_confidence": 0.884,
    "pagerank": {
      "raw": 6.89946925098513e-08,
      "percentile": 0.41951345425930237
    },
    "sha256": "a8c44c08fe1d7d22a4f2e6a4a2f63cb20e34fe653fd6a79d729b80dedd63db33",
    "simhash": "1:85b7f7da57580734",
    "word_count": 3563
  },
  "last_updated": "2024-02-27T17:56:26.592595+00:00",
  "provenance": {
    "date_added": "2019-08-29",
    "source": "Harvard",
    "batch": "2018"
  },
  "file_name": "0834-01",
  "first_page_order": 860,
  "last_page_order": 869
}